<?xml version="1.0" encoding="iso-8859-1"?>
<mosinstall type="template" version="1.0.x">
	<name>Unicaribe</name>
	<creationDate>4/05/12</creationDate>
	<author>doubleclickweb</author>
	<copyright>doubleclickweb</copyright>
	<authorEmail>doubleclickweb@mail.com</authorEmail>
	<authorUrl>www.doubleclickweb.com</authorUrl>
	<version>1.0</version>
	<description>University by doubleclickweb. Unique layout options and color variations.
		<![CDATA[
			<h1>University Joomla  Template by doubleclickweb</h1>

			<img src="../templates/university/images/logotm.jpg" /><br />University Joomla  Template by doubleclickweb.   This  template is for members of the Youjoomla Joomla Template Club only. <a href="http://www.doubleclickweb.com">Youjoomla Temlplates Club</a> home page.
<br></br>
			
			<b>Version 1.0.0</b><br />
			<ul>
			<li>Initial Release</li>
			</ul>

			]]></description>
	<files>
		<filename>head.php</filename>
		<filename>index.php</filename>
		<filename>settings.php</filename>
		<filename>styleswitcher.php</filename>
		<filename>suckerfish.php</filename>
		<filename>tools.php</filename>
		<filename>css/iepngfix.htc</filename>
		<filename>css/index.html</filename>
		<filename>images/index.html</filename>
		<filename>images/typ/index.html</filename>
		<filename>sifr/Arno.swf</filename>
		<filename>sifr/Iskola.swf</filename>
		<filename>sifr/sifr.js</filename>
		<filename>sifr/Tradegothic.swf</filename>
		<filename>sifr/Vipnagorgialla.swf</filename>
		<filename>src/ie.js</filename>
		<filename>src/ie2.js</filename>
		<filename>src/index.html</filename>
		<filename>src/mootools.v1.1.js</filename>
		<filename>src/mouseover.js</filename>
		<filename>src/sve.js</filename>
	</files>
	<images>
		<filename>css/blank.gif</filename>
		<filename>images/activeal.gif</filename>
		<filename>images/activeal_green.gif</filename>
		<filename>images/activeal_orange.gif</filename>
		<filename>images/activeal_red.gif</filename>
		<filename>images/activear.gif</filename>
		<filename>images/activear_green.gif</filename>
		<filename>images/activear_orange.gif</filename>
		<filename>images/activear_red.gif</filename>
		<filename>images/activehl.gif</filename>
		<filename>images/activehl_green.gif</filename>
		<filename>images/activehl_orange.gif</filename>
		<filename>images/activehl_red.gif</filename>
		<filename>images/activehr.gif</filename>
		<filename>images/activehr_green.gif</filename>
		<filename>images/activehr_orange.gif</filename>
		<filename>images/activehr_red.gif</filename>
		<filename>images/arrow.png</filename>
		<filename>images/bl.gif</filename>
		<filename>images/blue.gif</filename>
		<filename>images/bl_blue.gif</filename>
		<filename>images/bl_green.gif</filename>
		<filename>images/bl_orange.gif</filename>
		<filename>images/bl_red.gif</filename>
		<filename>images/br.gif</filename>
		<filename>images/br_blue.gif</filename>
		<filename>images/br_green.gif</filename>
		<filename>images/br_orange.gif</filename>
		<filename>images/br_red.gif</filename>
		<filename>images/bwl.gif</filename>
		<filename>images/bwr.gif</filename>
		<filename>images/bww.gif</filename>
		<filename>images/emailButton.png</filename>
		<filename>images/ff.gif</filename>
		<filename>images/fl.gif</filename>
		<filename>images/fluid.gif</filename>
		<filename>images/fr.gif</filename>
		<filename>images/gr.gif</filename>
		<filename>images/green.gif</filename>
		<filename>images/h3.gif</filename>
		<filename>images/headerbg.gif</filename>
		<filename>images/headl.gif</filename>
		<filename>images/headr.gif</filename>
		<filename>images/indent1.png</filename>
		<filename>images/indent2.png</filename>
		<filename>images/indent3.png</filename>
		<filename>images/indent4.png</filename>
		<filename>images/inswrbg.gif</filename>
		<filename>images/large.gif</filename>
		<filename>images/linija.gif</filename>
		<filename>images/linija1.gif</filename>
		<filename>images/logo.gif</filename>
		<filename>images/logotm.jpg</filename>
		<filename>images/logo_green.gif</filename>
		<filename>images/logo_orange.gif</filename>
		<filename>images/logo_red.gif</filename>
		<filename>images/medium.gif</filename>
		<filename>images/narrow.gif</filename>
		<filename>images/orange.gif</filename>
		<filename>images/password.gif</filename>
		<filename>images/pdf_button.png</filename>
		<filename>images/printButton.png</filename>
		<filename>images/readon.gif</filename>
		<filename>images/red.gif</filename>
		<filename>images/searchng.gif</filename>
		<filename>images/sl.gif</filename>
		<filename>images/sl_green.gif</filename>
		<filename>images/sl_orange.gif</filename>
		<filename>images/sl_red.gif</filename>
		<filename>images/small.gif</filename>
		<filename>images/sr.gif</filename>
		<filename>images/sr_green.gif</filename>
		<filename>images/sr_orange.gif</filename>
		<filename>images/sr_red.gif</filename>
		<filename>images/ss.gif</filename>
		<filename>images/ss_green.gif</filename>
		<filename>images/ss_orange.gif</filename>
		<filename>images/ss_red.gif</filename>
		<filename>images/strelica_blue.gif</filename>
		<filename>images/strelica_green.gif</filename>
		<filename>images/strelica_orange.gif</filename>
		<filename>images/strelica_red.gif</filename>
		<filename>images/tl.gif</filename>
		<filename>images/tl_blue.gif</filename>
		<filename>images/tl_green.gif</filename>
		<filename>images/tl_orange.gif</filename>
		<filename>images/tl_red.gif</filename>
		<filename>images/tr.gif</filename>
		<filename>images/tr_blue.gif</filename>
		<filename>images/tr_green.gif</filename>
		<filename>images/tr_orange.gif</filename>
		<filename>images/tr_red.gif</filename>
		<filename>images/username.gif</filename>
		<filename>images/wide.gif</filename>
		<filename>images/wrapbg.gif</filename>
		<filename>images/round/bb.gif</filename>
		<filename>images/round/bb_top.gif</filename>
		<filename>images/round/blc.gif</filename>
		<filename>images/round/blc_top.gif</filename>
		<filename>images/round/brc.gif</filename>
		<filename>images/round/brc_top.gif</filename>
		<filename>images/round/l.gif</filename>
		<filename>images/round/l_top.gif</filename>
		<filename>images/round/r.gif</filename>
		<filename>images/round/r_top.gif</filename>
		<filename>images/round/tb.gif</filename>
		<filename>images/round/tb_top.gif</filename>
		<filename>images/round/tlc.gif</filename>
		<filename>images/round/tlc_top.gif</filename>
		<filename>images/round/trc.gif</filename>
		<filename>images/round/trc_top.gif</filename>
		<filename>images/typ/check.png</filename>
		<filename>images/typ/checkg.gif</filename>
		<filename>images/typ/check_b.png</filename>
		<filename>images/typ/clip.jpg</filename>
		<filename>images/typ/down.jpg</filename>
		<filename>images/typ/error.gif</filename>
		<filename>images/typ/info.gif</filename>
		<filename>images/typ/pin.gif</filename>
		<filename>images/typ/pin.jpg</filename>
		<filename>images/typ/qlg.gif</filename>
		<filename>images/typ/qrg.gif</filename>
		<filename>images/typ/star.png</filename>
		<filename>images/typ/stargray.jpg</filename>
		<filename>images/typ/star_b.png</filename>
		<filename>images/typ/sticky.jpg</filename>
		<filename>images/typ/tips.gif</filename>
		<filename>template_thumbnail.png</filename>
	</images>
	<css>
		<filename>css/blue.css</filename>
		<filename>css/green.css</filename>
		<filename>css/layout.css</filename>
		<filename>css/orange.css</filename>
		<filename>css/red.css</filename>
		<filename>css/template_css.css</filename>
		<filename>sifr/sscreen.css</filename>
	</css>
</mosinstall>
